hummus/__init__.py
hummus/embed.py
hummus/file.py
hummus/guild.py
hummus/http.py
hummus/main.py
hummus/message.py
hummus/ready.py
hummus/role.py
hummus/user.py
hummus/internal/__init__.py
hummus/internal/message.py
hummus/internal/http/__init__.py
hummus/internal/http/channel.py
hummus/internal/http/guild.py
hummus/internal/http/message.py
hummus/internal/http/self.py
hummus/internal/http/user.py
hummus/utils/__init__.py
hummus/utils/commands.py
hummus/utils/context.py
hummus/utils/enums.py
hummus/utils/exceptions.py
hummus/utils/extras.py
hmus-1.1.3.dist-info/METADATA
hmus-1.1.3.dist-info/WHEEL
hmus-1.1.3.dist-info/top_level.txt
hmus-1.1.3.dist-info/RECORD
