Metadata-Version: 2.1
Name: hmus
Version: 1.1.3
Summary: An asynchronous API wrapper for Hummus by Ziad87
Home-page: https://github.com/LG125YT/Hummus.py
Author: LG125YT
Author-email: lg125yt@gmail.com
License: UNKNOWN
Platform: UNKNOWN
Classifier: Development Status :: 4 - Beta
Classifier: Intended Audience :: Developers
Classifier: License :: OSI Approved :: MIT License
Classifier: Operating System :: OS Independent
Classifier: Programming Language :: Python
Classifier: Programming Language :: Python :: 3
Classifier: Programming Language :: Python :: 3.6
Classifier: Programming Language :: Python :: 3.7
Classifier: Programming Language :: Python :: 3.8
Classifier: Programming Language :: Python :: 3.9
Classifier: Programming Language :: Python :: 3.10
Classifier: Programming Language :: Python :: 3.11
Requires-Dist: Pillow
Requires-Dist: asyncio
Requires-Dist: datetime
Requires-Dist: fake-useragent
Requires-Dist: filetype
Requires-Dist: requests
Requires-Dist: requests-toolbelt
Requires-Dist: typing
Requires-Dist: websockets
